filters/CousinsI.csv
filters/CousinsR.csv
filters/JohnsonB.csv
filters/JohnsonI.csv
filters/JohnsonR.csv
filters/JohnsonU.csv
filters/JohnsonV.csv
filters/Kepler.csv
filters/SLOAN_g.csv
filters/SLOAN_gprime.csv
filters/SLOAN_i.csv
filters/SLOAN_iprime.csv
filters/SLOAN_r.csv
filters/SLOAN_rprime.csv
filters/SLOAN_u.csv
filters/SLOAN_uprime.csv
filters/SLOAN_z.csv
filters/SLOAN_zprime.csv
filters/TESS.csv
transitfit/__init__.py
transitfit/_ldtk_handler.py
transitfit/_likelihood.py
transitfit/_limb_darkening_handler.py
transitfit/_paramarray.py
transitfit/_params.py
transitfit/_pipeline.py
transitfit/_utils.py
transitfit/detrender.py
transitfit/detrending_funcs.py
transitfit/error_analysis.py
transitfit/io.py
transitfit/lightcurve.py
transitfit/output_handler.py
transitfit/plotting.py
transitfit/priorinfo.py
transitfit/retriever.py
transitfit/time_conversions.py
transitfit-3.4.1.dist-info/LICENSE
transitfit-3.4.1.dist-info/METADATA
transitfit-3.4.1.dist-info/WHEEL
transitfit-3.4.1.dist-info/top_level.txt
transitfit-3.4.1.dist-info/RECORD
