Metadata-Version: 2.1
Name: transitfit
Version: 3.4.1
Summary: A package to fit exoplanet transit light curves
Home-page: https://github.com/SPEARNET/TransitFit
Author: Joshua Hayes and collaborators
Author-email: Eamonn.Kerins@manchester.ac.uk
Project-URL: Documentation, https://transitfit.readthedocs.io/en/latest/index.html
Keywords: exoplanets,transits,fitting
Classifier: Programming Language :: Python :: 3
Classifier: License :: OSI Approved :: MIT License
Classifier: Operating System :: OS Independent
Classifier: Development Status :: 4 - Beta
Requires-Python: >=3.6
License-File: LICENSE
Requires-Dist: numpy
Requires-Dist: batman-package
Requires-Dist: dynesty
Requires-Dist: matplotlib
Requires-Dist: pandas
Requires-Dist: ldtk (>=1.5.0)
Requires-Dist: corner
Requires-Dist: semantic-version
Requires-Dist: scipy
Requires-Dist: statsmodels
